mss/100-500.csv
mss/__init__.py
mss/align.py
mss/alignment.py
mss/dm.py
mss/expire_alignment.py
mss/expire_mssdata.py
mss/frag.py
mss/model_5_3_14_4_48.h5
mss/mssdata.py
mss/mssmain.py
mss/rfmodel_tuned.pkl
mss/version.py
mss/visreader.py
mss/tests/__init__.py
mss/tests/test_alignment.py
mss/tests/test_dm.py
mss/tests/test_mssmain.py
mss/tests/test_visreader.py
mass_suite-1.1.2.dist-info/LICENSE
mass_suite-1.1.2.dist-info/METADATA
mass_suite-1.1.2.dist-info/WHEEL
mass_suite-1.1.2.dist-info/top_level.txt
mass_suite-1.1.2.dist-info/RECORD
