Metadata-Version: 2.1
Name: mass-suite
Version: 1.1.2
Summary: A package for HRMS data analysis
Home-page: https://github.com/XiminHu/mass-suite
Author: Ximin Hu, Derek Mar, Nozomi Suzuki, Bowei Zhang
Author-email: xhu66@uw.edu
Classifier: Programming Language :: Python :: 3
Classifier: License :: OSI Approved :: MIT License
Classifier: Operating System :: OS Independent
Requires-Python: >=3.6
License-File: LICENSE
